LICENSE
MANIFEST.in
README.md
setup.py
twint/__init__.py
twint/__version__.py
twint/config.py
twint/datelock.py
twint/feed.py
twint/format.py
twint/get.py
twint/output.py
twint/run.py
twint/tweet.py
twint/url.py
twint/user.py
twint/verbose.py
twint.egg-info/PKG-INFO
twint.egg-info/SOURCES.txt
twint.egg-info/dependency_links.txt
twint.egg-info/requires.txt
twint.egg-info/top_level.txt
twint/storage/__init__.py
twint/storage/db.py
twint/storage/elasticsearch.py
twint/storage/panda.py
twint/storage/write.py
twint/storage/write_meta.py