Metadata-Version: 1.2
Name: twint
Version: 1.2.0.0
Summary: An advanced Twitter scraping & OSINT tool.
Home-page: https://github.com/twintproject/twint
Author: Cody Zacharias
Author-email: codyzacharias@pm.me
License: MIT
Platform: UNKNOWN
Classifier: License :: OSI Approved :: MIT License
Classifier: Programming Language :: Python
Classifier: Programming Language :: Python :: 3
Classifier: Programming Language :: Python :: 3.5
Classifier: Programming Language :: Python :: 3.6
Requires-Python: >=3.5.0
